deltau/__init__.py
deltau/setup.py
deltau/core/__init__.py
deltau/core/backtester.py
deltau/core/data_loader.py
deltau/visualization/__init__.py
deltau/visualization/tear_sheet.py
DeltaU-1.1.0.dist-info/METADATA
DeltaU-1.1.0.dist-info/WHEEL
DeltaU-1.1.0.dist-info/top_level.txt
DeltaU-1.1.0.dist-info/RECORD
