Metadata-Version: 2.2
Name: DeltaU
Version: 1.1.0
Summary: A backtesting and performance analysis package
Home-page: https://github.com/9inoxx/DeltaU
Author: Julian Fortis
Classifier: Programming Language :: Python :: 3
Classifier: License :: OSI Approved :: MIT License
Classifier: Operating System :: OS Independent
Requires-Python: >=3.11.7
Requires-Dist: pandas
Requires-Dist: plotly
Requires-Dist: nbformat>=4.2.0
Dynamic: author
Dynamic: classifier
Dynamic: description
Dynamic: description-content-type
Dynamic: home-page
Dynamic: requires-dist
Dynamic: requires-python
Dynamic: summary
